{
    "category": "Definitions",
    "risk_type": "compliance",
    "conditions": "",
    "jurisdiction": "Global",
    "summary": "Disclosure requirement for prospective arbitrators",
    "clause_id": "0741a022-af1e-48d0-8985-211a3e407bf8",
    "text": "9 1[(8) The Supreme Court or, as the case may be, the High Court or the person or institution designated by such Court, before appointing an arbitrator, shall seek a disclosure in writing from the prospective arbitrator in terms of sub-section (1) of section 12, and have due regard to\u2014 (a) any qualifications required for the arbitrator by the agreement of the parties",
    "flesch_score": 5.918571428571454,
    "industry": "Logistics"
}