{
    "category": "Dispute Resolution",
    "risk_type": "general",
    "conditions": "",
    "jurisdiction": "Unknown",
    "summary": "Written invitation to conciliate",
    "clause_id": "1d5d4811-c6e7-4ee2-a1aa-d57753c1cbd1",
    "text": "Commencement of conciliation proceedings.\u2014(1) The party initiating conciliation shall send to the other party a written invitation to conciliate under this Part, briefly identifying the subject of the dispute",
    "flesch_score": 8.331293103448274,
    "industry": "Logistics"
}