{
    "category": "Definitions",
    "risk_type": "Compliance",
    "conditions": "",
    "jurisdiction": "Global",
    "summary": "Definition of finality in judicial decisions",
    "clause_id": "38e5687b-89a5-45bb-b2ed-8eda80058770",
    "text": "(iii) in sub-section (7), for the words \u201cthe Chief Justice or the person or institution designated by him is final\u201d, the words \u201cthe Supreme Court or, as the case may be, the High Court or the person or institution designated by such Court is final and no appeal including Letters Patent Appeal shall lie against such decision\u201d shall be substituted",
    "flesch_score": 16.215000000000003,
    "industry": "Logistics"
}