{
    "category": "Definitions",
    "risk_type": "general",
    "conditions": "",
    "jurisdiction": "Unknown",
    "summary": "Definition of conciliator in conciliation proceedings",
    "clause_id": "44e9e440-a095-4df3-b57d-94165c1b52b5",
    "text": "Appointment of conciliators.\u2014(1) Subject to sub-section (2)\u2014 (a) in conciliation proceedings, with one conciliator, the parties may agree on the name of a sole conciliator",
    "flesch_score": 28.331500000000034,
    "industry": "Logistics"
}