{
    "category": "Definitions",
    "risk_type": "general",
    "conditions": "",
    "jurisdiction": "India",
    "summary": "Definition of weekly rest period",
    "clause_id": "544f7cfe-db7e-4632-80a2-eb3ab7d9c990",
    "text": "Weekly rest.--(1) The State Government may, by notification in the Official Gazette, make rules providing for a day of rest in every period of seven days, which shall be allowed to all motor transport workers",
    "flesch_score": 35.95000000000002,
    "industry": "Logistics"
}