{
    "classification": {
        "category": "Dispute Resolution",
        "risk_type": "delay",
        "conditions": "",
        "jurisdiction": "Global"
    },
    "summary": "Agreement to submit to arbitration for defined legal relationship",
    "clause_id": "8978ee1b-12a5-43ab-9588-1605babf0495",
    "text": "Each Contracting State shall recognise an agreement in writing under which the parties undertake to submit to arbitration all or any differences which have arisen or which may arise between them in respect of defined legal relationship, whether contractual or not, concerning a subject-matter capable of settlement by arbitration",
    "flesch_score": -3.467346938775478,
    "industry": "Logistics"
}