{
    "category": "Termination",
    "risk_type": "delay",
    "conditions": "",
    "jurisdiction": "Global",
    "summary": "Prohibition on party's representation in other proceedings",
    "clause_id": "9cabb7f2-8bbf-4b0c-b15e-0404d6c7f5f7",
    "text": "Role of conciliator in other proceedings.\u2014Unless otherwise agreed by the parties,\u2014 (a) the conciliator shall not act as an arbitrator or as a representative or counsel of a party in any arbitral or judicial proceeding in respect of a dispute that is the subject of the conciliation proceedings",
    "flesch_score": 23.850000000000023,
    "industry": "Logistics"
}