{
    "category": "Definitions",
    "risk_type": "compliance",
    "conditions": "",
    "jurisdiction": "Unknown",
    "summary": "Leave excludes holidays and festival days",
    "clause_id": "9efc2b2b-7318-4a1d-8d89-ca11af0453b5",
    "text": "Explanation.--For the purposes of this section, leave shall not include weekly holidays or holidays for festival or other similar occasions whether occurring during or at either end of the period of leave",
    "flesch_score": 18.37375000000003,
    "industry": "Logistics"
}