{
    "category": "Termination",
    "risk_type": "none",
    "conditions": "",
    "jurisdiction": "India",
    "summary": "State Government can apply the act to undertakings with fewer than 5 workers with prior notice",
    "clause_id": "9f99fab6-c022-4460-bfea-6f412a736af6",
    "text": "(4) It applies to every motor transport undertaking employing five or more motor transport workers : Provided that the state Government may, after giving not less than two months\u2019 notice of its intention so to do, by notification in the Official Gazette, apply all or any of the provisions of this Act to any motor transport undertaking employing less than five motor transport workers",
    "flesch_score": -0.7957142857142685,
    "industry": "Logistics"
}