{
    "category": "Definitions",
    "risk_type": "compliance",
    "conditions": "",
    "jurisdiction": "Global",
    "summary": "Applicability of criminal procedure code for search and seizure",
    "clause_id": "aba6a9b3-0480-4cef-9e60-63484e65d141",
    "text": "(2) The provisions of the Code of criminal Procedure, 1898 (5 of 1898), shall, so far as may be, apply to any search or seizure under this section as they apply to any search or seizure made under the authority of a warrant issued under section 98 of the said Code",
    "flesch_score": 33.9758823529412,
    "industry": "Logistics"
}