{
    "category": "Termination",
    "risk_type": "delay",
    "conditions": "",
    "jurisdiction": "Global",
    "summary": "Filing of an application to set aside arbitral award does not automatically render it unenforceable",
    "clause_id": "af1b7c96-f2cf-44ce-8e6b-9062ebf890f4",
    "text": "(2) Where an application to set aside the arbitral award has been filed in the Court under section 34, the filing of such an application shall not by itself render that award unenforceable, unless the Court grants an order of stay of the operation of the said arbitral award in accordance with the provisions of sub-section (3), on a separate application made for that purpose",
    "flesch_score": 4.198461538461572,
    "industry": "Logistics"
}