{
    "category": "Dispute Resolution",
    "risk_type": "general",
    "conditions": "",
    "jurisdiction": "Global",
    "summary": "Language to be used in arbitral proceedings determined by tribunal",
    "clause_id": "c76f89a8-7f70-4046-85a0-75db374c0896",
    "text": "(2) Failing any agreement referred to in sub-section (1), the arbitral tribunal shall determine the language or languages to be used in the arbitral proceedings",
    "flesch_score": 29.180000000000007,
    "industry": "Logistics"
}