{
    "category": "Termination",
    "risk_type": "compliance",
    "conditions": "",
    "jurisdiction": "Global",
    "summary": "Clause regarding reciprocity for recognizing and enforcing Convention awards",
    "clause_id": "f06462a0-e62d-4159-b7e0-9fe264c22f98",
    "text": "When signing, ratifying or acceding to this Convention, or notifying extension under article X hereof, any State may on the basis of reciprocity declare that it will apply the Convention to the recognition and enforcement of awards made only in the territory of another Contracting State",
    "flesch_score": 0.14065217391305396,
    "industry": "Logistics"
}